wumpy/gateway/__init__.py
wumpy/gateway/_errors.py
wumpy/gateway/_shard.py
wumpy/gateway/_utils.py
wumpy/gateway/py.typed
wumpy_gateway-0.3.0.dist-info/WHEEL
wumpy_gateway-0.3.0.dist-info/METADATA
wumpy_gateway-0.3.0.dist-info/RECORD
